azuresphere_imagemetadata/LICENSE
azuresphere_imagemetadata/README.md
azuresphere_imagemetadata/__init__.py
azuresphere_imagemetadata/exceptions.py
azuresphere_imagemetadata/guid_utils.py
azuresphere_imagemetadata/image.py
azuresphere_imagemetadata/image_manifest.py
azuresphere_imagemetadata/image_metadata.py
azuresphere_imagemetadata/certificates/app_test_sign.pfx
azuresphere_imagemetadata/certificates/tp_app_test_sign.cer
azuresphere_imagemetadata/metadata_headers/__init__.py
azuresphere_imagemetadata/metadata_headers/image_metadata.py
azuresphere_imagemetadata/metadata_headers/image_metadata_section.py
azuresphere_imagemetadata/metadata_sections/__init__.py
azuresphere_imagemetadata/metadata_sections/abi.py
azuresphere_imagemetadata/metadata_sections/compression.py
azuresphere_imagemetadata/metadata_sections/debug.py
azuresphere_imagemetadata/metadata_sections/identity.py
azuresphere_imagemetadata/metadata_sections/image_policy.py
azuresphere_imagemetadata/metadata_sections/metadata.py
azuresphere_imagemetadata/metadata_sections/metadata_id.py
azuresphere_imagemetadata/metadata_sections/not_implemented.py
azuresphere_imagemetadata/metadata_sections/required_offset.py
azuresphere_imagemetadata/metadata_sections/revocation.py
azuresphere_imagemetadata/metadata_sections/signature.py
azuresphere_imagemetadata/metadata_sections/temporary_image.py
azuresphere_imagemetadata/metadata_sections/utils.py
azuresphere_imagemetadata/metadata_sections/internal/__init__.py
azuresphere_imagemetadata/metadata_sections/internal/capabilities.py
azuresphere_imagemetadata/metadata_sections/internal/onebl.py
azuresphere_imagemetadata/signing/__init__.py
azuresphere_imagemetadata/signing/app_development.py
azuresphere_imagemetadata/signing/der_encoded.py
azuresphere_imagemetadata/signing/signer.py
azuresphere_imagemetadata/signing/signing_info.py
azuresphere_imagemetadata-0.2.1.dist-info/METADATA
azuresphere_imagemetadata-0.2.1.dist-info/WHEEL
azuresphere_imagemetadata-0.2.1.dist-info/top_level.txt
azuresphere_imagemetadata-0.2.1.dist-info/RECORD
