Metadata-Version: 2.4
Name: azuresphere_imagemetadata
Version: 0.2.1
Summary: A library for parsing and composing image metadata for azure sphere devices
Author-email: Microsoft <azspheremfrsamplesup@microsoft.com>
License: Copyright (c) Microsoft Corporation.
Keywords: azure,sphere,device,image,metadata
Classifier: License :: OSI Approved :: MIT License
Classifier: Programming Language :: Python :: 3
Classifier: Operating System :: OS Independent
Requires-Python: >=3.8
Requires-Dist: cryptography>=41.0.2
